toolbox/__main__.py
toolbox_cli-0.0.7.dist-info/METADATA
toolbox_cli-0.0.7.dist-info/WHEEL
toolbox_cli-0.0.7.dist-info/entry_points.txt
toolbox_cli-0.0.7.dist-info/top_level.txt
toolbox_cli-0.0.7.dist-info/RECORD
