Metadata-Version: 2.1
Name: toolbox-cli
Version: 0.0.7
Summary: A toolbox that runs in Command Line Interface.
Home-page: UNKNOWN
Author: meowmeowcat
Author-email: 
License: UNKNOWN
Platform: UNKNOWN
Classifier: Programming Language :: Python :: 3
Classifier: License :: OSI Approved :: MIT License
Classifier: Operating System :: OS Independent
Requires-Python: >=3.6
Requires-Dist: colorama
